<?xml version="1.0" encoding="UTF-8" standalone="no"?>
<tns:database xmlns:tns="http://www.iw.com/sns/platform/" xmlns:xsi="http://www.w3.org/2001/XMLSchema-instance">
	<Group id="mecha_skill">
		<ItemSpec id="1" type="0" target="0" first_round="1" cd="5" combo_max="8" energy_add="100" base_attack_rate="1000" up_attack_rate="100" range="0" desc_lvlup="200;30|100;20" icon="FB_IC_beishuiyizhan_SKILL" action="wq_bishou_01_atk01" action_effect="wq_bishou_jin_pugong_zhengmian;wq_bishou_jin_pugong_fanmian" hit_effect="wq_bishou_jin_pugong_shouji" combo_skillid="3" critic_rate="200" critic_damage_rate="2500"/>
		<ItemSpec id="2" name="209770" type="1" combo_max="4" energy_add="0" base_attack_rate="1200" up_attack_rate="500" energy_limit="100" critic_damage_rate="1000" icon="FB_IC_beishuiyizhan_SKILL" range="0" action="wq_bishou_01_atk03" action_effect="wq_bishou_jin_dazhao_zhengmian;wq_bishou_jin_dazhao_fanmian" hit_effect="wq_bishou_jin_dazhao_shouji" target="0"/>
		<ItemSpec id="3" type="2" combo_max="4" energy_add="5" base_attack_rate="800" up_attack_rate="200" icon="FB_IC_beishuiyizhan_SKILL" range="0" action="wq_bishou_01_atk01" action_effect="wq_bishou_jin_lianji_zhengmian;wq_bishou_jin_lianji_fanmian" hit_effect="wq_bishou_jin_lianji_shouji" target="0"/>
		<ItemSpec id="101" type="0" action_effect="wq_bishou_jin_pugong_zhengmian;wq_bishou_jin_pugong_fanmian" hit_effect="wq_bishou_jin_pugong_shouji" target="0" first_round="3" cd="3" combo_max="8" energy_add="50" base_attack_rate="1000" up_attack_rate="100" icon="FB_IC_beishuiyizhan_SKILL" range="0" action="wq_bishou_01_atk01"/>
		<ItemSpec id="102" type="1" action_effect="wq_bishou_jin_dazhao_zhengmian;wq_bishou_jin_dazhao_fanmian" hit_effect="wq_bishou_jin_dazhao_shouji" target="0" combo_max="4" base_attack_rate="4000" up_attack_rate="800" energy_limit="100" icon="FB_IC_beishuiyizhan_SKILL" range="0" action="wq_bishou_01_atk03" name="209771" energy_add="0"/>
		<ItemSpec id="103" type="2" action_effect="wq_bishou_jin_lianji_zhengmian;wq_bishou_jin_lianji_fanmian" hit_effect="wq_bishou_jin_lianji_shouji" target="0" combo_max="4" energy_add="5" base_attack_rate="500" up_attack_rate="200" icon="FB_IC_beishuiyizhan_SKILL" range="0" action="wq_bishou_01_atk01"/>
		<ItemSpec id="104" type="0" action_effect="wq_changdao_jin_pugong_zhengmian;wq_changdao_jin_pugong_fanmian" hit_effect="wq_changdao_jin_pugong_shouji" target="0" first_round="3" cd="3" combo_max="8" energy_add="50" base_attack_rate="1000" up_attack_rate="100" icon="FB_IC_beishuiyizhan_SKILL" range="0" action="wq_changdao_01_atk01"/>
		<ItemSpec id="105" type="1" action_effect="wq_changdao_jin_dazhao_zhengmian;wq_changdao_jin_dazhao_fanmian" hit_effect="wq_changdao_jin_dazhao_shouji" target="0" combo_max="4" base_attack_rate="4000" up_attack_rate="800" energy_limit="100" icon="FB_IC_beishuiyizhan_SKILL" range="0" action="wq_changdao_01_atk03" name="209771" energy_add="0"/>
		<ItemSpec id="106" type="2" action_effect="wq_changdao_jin_lianji_zhengmian;wq_changdao_jin_lianji_fanmian" hit_effect="wq_changdao_jin_lianji_shouji" target="0" combo_max="4" energy_add="5" base_attack_rate="500" up_attack_rate="200" icon="FB_IC_beishuiyizhan_SKILL" range="0" action="wq_changdao_01_atk01"/>
		<ItemSpec id="107" type="0" action_effect="wq_shuangshoufu_jin_pugong_zhengmian;wq_shuangshoufu_jin_pugong_fanmian" hit_effect="wq_shuangshoufu_jin_pugong_shouji" target="0" first_round="3" cd="3" combo_max="8" energy_add="50" base_attack_rate="1000" up_attack_rate="100" icon="FB_IC_beishuiyizhan_SKILL" range="0" action="wq_shuangshoufu_01_atk01"/>
		<ItemSpec id="108" type="1" action_effect="wq_shuangshoufu_jin_dazhao_zhengmian;wq_shuangshoufu_jin_dazhao_fanmian" hit_effect="wq_shuangshoufu_jin_dazhao_shouji" target="0" combo_max="4" base_attack_rate="4000" up_attack_rate="800" energy_limit="100" icon="FB_IC_beishuiyizhan_SKILL" range="0" action="wq_shuangshoufu_01_atk03" name="209771" energy_add="0"/>
		<ItemSpec id="109" type="2" action_effect="wq_shuangshoufu_jin_lianji_zhengmian;wq_shuangshoufu_jin_lianji_fanmian" hit_effect="wq_shuangshoufu_jin_lianji_shouji" target="0" combo_max="4" energy_add="5" base_attack_rate="500" up_attack_rate="200" icon="FB_IC_beishuiyizhan_SKILL" range="0" action="wq_shuangshoufu_01_atk01"/>
		<ItemSpec id="110" type="0" action_effect="wq_shouqiang_yuan_pugong_kaihuo" hit_effect="wq_shouqiang_yuan_pugong_shouji" bullet_effect="wq_shouqiang_yuan_pugong_zidan" target="0" first_round="3" cd="3" combo_max="8" energy_add="50" base_attack_rate="1000" up_attack_rate="100" icon="FB_IC_beishuiyizhan_SKILL" range="0" action="wq_shouqiang_01_atk01"/>
		<ItemSpec id="111" type="1" action_effect="wq_shouqiang_yuan_dazhao_kaihuo" hit_effect="wq_shouqiang_yuan_dazhao_shouji" bullet_effect="wq_shouqiang_yuan_dazhao_zidan" target="0" combo_max="4" base_attack_rate="4000" up_attack_rate="800" energy_limit="100" icon="FB_IC_beishuiyizhan_SKILL" range="0" action="wq_shouqiang_01_atk03" name="209771" energy_add="0"/>
		<ItemSpec id="112" type="2" action_effect="wq_shouqiang_yuan_lianji_kaihuo" hit_effect="wq_shouqiang_yuan_lianji_shouji" bullet_effect="wq_shouqiang_yuan_lianji_zidan" target="0" combo_max="4" energy_add="5" base_attack_rate="500" up_attack_rate="200" icon="FB_IC_beishuiyizhan_SKILL" range="1" action="wq_shouqiang_01_atk01"/>
		<ItemSpec id="113" type="0" action_effect="wq_chongfengqiang_yuan_pugong_kaihuo" hit_effect="wq_chongfengqiang_yuan_pugong_shouji" bullet_effect="wq_chongfengqiang_yuan_pugong_zidan" target="0" first_round="3" cd="3" combo_max="8" energy_add="50" base_attack_rate="1000" up_attack_rate="100" icon="FB_IC_beishuiyizhan_SKILL" range="0" action="wq_chongfengqiang_01_atk01"/>
		<ItemSpec id="114" type="1" action_effect="wq_chongfengqiang_yuan_dazhao_kaihuo" hit_effect="wq_chongfengqiang_yuan_dazhao_shouji" bullet_effect="wq_chongfengqiang_yuan_dazhao_zidan;0.1;0.3;0.5" target="0" combo_max="4" base_attack_rate="4000" up_attack_rate="800" energy_limit="100" icon="FB_IC_beishuiyizhan_SKILL" range="0" action="wq_chongfengqiang_01_atk03" name="209771" energy_add="0"/>
		<ItemSpec id="115" type="2" action_effect="wq_chongfengqiang_yuan_lianji_kaihuo" hit_effect="wq_chongfengqiang_yuan_lianji_shouji" bullet_effect="wq_chongfengqiang_yuan_lianji_zidan" target="0" combo_max="4" energy_add="5" base_attack_rate="500" up_attack_rate="200" icon="FB_IC_beishuiyizhan_SKILL" range="1" action="wq_chongfengqiang_01_atk01"/>
		<ItemSpec id="116" type="0" action_effect="wq_jujiqiang_yuan_pugong_kaihuo" hit_effect="wq_jujiqiang_yuan_pugong_shouji" bullet_effect="wq_jujiqiang_yuan_pugong_zidan" target="0" first_round="3" cd="3" combo_max="8" energy_add="50" base_attack_rate="1000" up_attack_rate="100" icon="FB_IC_beishuiyizhan_SKILL" range="0" action="wq_jujiqiang_01_atk01"/>
		<ItemSpec id="117" type="1" action_effect="wq_jujiqiang_yuan_dazhao_kaihuo" hit_effect="wq_jujiqiang_yuan_dazhao_shouji" bullet_effect="wq_jujiqiang_yuan_dazhao_zidan" target="0" combo_max="4" base_attack_rate="4000" up_attack_rate="800" energy_limit="100" icon="FB_IC_beishuiyizhan_SKILL" range="0" action="wq_jujiqiang_01_atk03" name="209771" energy_add="0"/>
		<ItemSpec id="118" type="2" action_effect="wq_jujiqiang_yuan_lianji_kaihuo" hit_effect="wq_jujiqiang_yuan_lianji_shouji" bullet_effect="wq_jujiqiang_yuan_lianji_zidan" target="0" combo_max="4" energy_add="5" base_attack_rate="500" up_attack_rate="200" icon="FB_IC_beishuiyizhan_SKILL" range="1" action="wq_jujiqiang_01_atk01"/>
		<ItemSpec id="119" type="0" action_effect="wq_liudanqiang_yuan_pugong_kaihuo" hit_effect="wq_liudanqiang_yuan_pugong_shouji" bullet_effect="wq_liudanqiang_yuan_pugong_zidan" target="0" first_round="3" cd="3" combo_max="8" energy_add="50" base_attack_rate="1000" up_attack_rate="100" icon="FB_IC_beishuiyizhan_SKILL" range="0" action="wq_liudanqiang_01_atk01"/>
		<ItemSpec id="120" type="1" action_effect="wq_liudanqiang_yuan_dazhao_kaihuo" hit_effect="wq_liudanqiang_yuan_dazhao_shouji" bullet_effect="wq_liudanqiang_yuan_dazhao_zidan" target="0" combo_max="4" base_attack_rate="4000" up_attack_rate="800" energy_limit="100" icon="FB_IC_beishuiyizhan_SKILL" range="0" action="wq_liudanqiang_01_atk03" name="209771" energy_add="0"/>
		<ItemSpec id="121" type="2" action_effect="wq_liudanqiang_yuan_lianji_kaihuo" hit_effect="wq_liudanqiang_yuan_lianji_shouji" bullet_effect="wq_liudanqiang_yuan_lianji_zidan" target="0" combo_max="4" energy_add="5" base_attack_rate="500" up_attack_rate="200" icon="FB_IC_beishuiyizhan_SKILL" range="1" action="wq_liudanqiang_01_atk01"/>
		<ItemSpec id="122" type="0" action_effect="wq_huojianpao_yuan_pugong_kaihuo" hit_effect="wq_huojianpao_yuan_pugong_shouji" bullet_effect="wq_huojianpao_yuan_pugong_zidan" target="0" first_round="3" cd="3" combo_max="8" energy_add="50" base_attack_rate="1000" up_attack_rate="100" icon="FB_IC_beishuiyizhan_SKILL" range="0" action="wq_huojianpao_01_atk01"/>
		<ItemSpec id="123" type="1" action_effect="wq_huojianpao_yuan_dazhao_kaihuo" hit_effect="wq_huojianpao_yuan_dazhao_shouji" bullet_effect="wq_huojianpao_yuan_dazhao_zidan" target="0" combo_max="4" base_attack_rate="4000" up_attack_rate="800" energy_limit="100" icon="FB_IC_beishuiyizhan_SKILL" range="0" action="wq_huojianpao_01_atk03" name="209771" energy_add="0"/>
		<ItemSpec id="124" type="2" action_effect="wq_huojianpao_yuan_lianji_kaihuo" hit_effect="wq_huojianpao_yuan_lianji_shouji" bullet_effect="wq_huojianpao_yuan_lianji_zidan" target="0" combo_max="4" energy_add="5" base_attack_rate="500" up_attack_rate="200" icon="FB_IC_beishuiyizhan_SKILL" range="1" action="wq_huojianpao_01_atk01"/>
		<ItemSpec id="125" type="0" action_effect="wq_daodan_yuan_pugong_kaihuo" hit_effect="wq_daodan_yuan_pugong_shouji" bullet_effect="wq_daodan_yuan_pugong_zidan" target="0" first_round="3" cd="3" combo_max="8" energy_add="50" base_attack_rate="1000" up_attack_rate="100" icon="FB_IC_beishuiyizhan_SKILL" range="0" action="wq_daodan_01_atk01"/>
		<ItemSpec id="126" type="1" action_effect="wq_daodan_yuan_dazhao_kaihuo" hit_effect="wq_daodan_yuan_dazhao_shouji" bullet_effect="wq_daodan_yuan_dazhao_zidan" target="0" combo_max="4" base_attack_rate="4000" up_attack_rate="800" energy_limit="100" icon="FB_IC_beishuiyizhan_SKILL" range="0" action="wq_daodan_01_atk03" name="209771" energy_add="0"/>
		<ItemSpec id="127" type="2" action_effect="wq_daodan_yuan_lianji_kaihuo" hit_effect="wq_daodan_yuan_lianji_shouji" bullet_effect="wq_daodan_yuan_lianji_zidan" target="0" combo_max="4" energy_add="5" base_attack_rate="500" up_attack_rate="200" icon="FB_IC_beishuiyizhan_SKILL" range="1" action="wq_daodan_01_atk01"/>
		<ItemSpec id="1001" name="110400420" describe="110400423" type="0" icon="FB_IC_WS_shengbo" range="0" action="wq_shuangshoufu_01_atk01" action_effect="wq_shuangshoufu_jin_pugong_zhengmian;wq_shuangshoufu_jin_pugong_fanmian" hit_effect="wq_shuangshoufu_jin_pugong_shouji"/>
		<ItemSpec id="1002" type="0" range="1" icon="FB_IC_WS_leiting" action="wq_chongfengqiang_01_atk01" action_effect="wq_chongfengqiang_yuan_pugong_kaihuo" hit_effect="wq_chongfengqiang_yuan_pugong_shouji" name="110400421" bullet_effect="wq_chongfengqiang_yuan_pugong_zidan" describe="110400423"/>
		<ItemSpec id="1003" type="0" range="1" icon="FB_IC_WS_guangleng" action="wq_daodan_01_atk01" action_effect="wq_daodan_yuan_pugong_kaihuo" hit_effect="wq_daodan_yuan_pugong_shouji" name="110400422" bullet_effect="wq_daodan_yuan_pugong_zidan" describe="110400423"/>
	</Group>

</tns:database>